fastapi_mailer/__init__.py
fastapi_mailer/config.py
fastapi_mailer/connection.py
fastapi_mailer/email_utils/__init__.py
fastapi_mailer/email_utils/email_check.py
fastapi_mailer/email_utils/errors.py
fastapi_mailer/errors.py
fastapi_mailer/example.py
fastapi_mailer/fastmail.py
fastapi_mailer/msg.py
fastapi_mailer/schemas.py
fastapi_mailer-0.4.1.dist-info/LICENSE
fastapi_mailer-0.4.1.dist-info/WHEEL
fastapi_mailer-0.4.1.dist-info/METADATA
fastapi_mailer-0.4.1.dist-info/RECORD
