Metadata-Version: 2.1
Name: fastapi-mailer
Version: 0.4.1
Summary: Simple lightweight mail library for FastApi
License: MIT
Author: Sheyzi
Author-email: gistkiosk@gmail.com
Requires-Python: >=3.6.2,<4.0.0
Classifier: Intended Audience :: Developers
Classifier: License :: OSI Approved :: MIT License
Classifier: Operating System :: OS Independent
Classifier: Programming Language :: Python
Classifier: Programming Language :: Python :: 3
Classifier: Programming Language :: Python :: 3 :: Only
Classifier: Programming Language :: Python :: 3.10
Classifier: Programming Language :: Python :: 3.6
Classifier: Programming Language :: Python :: 3.7
Classifier: Programming Language :: Python :: 3.8
Classifier: Programming Language :: Python :: 3.9
Requires-Dist: Jinja2 (>=3.0.1,<4.0.0)
Requires-Dist: aioredis (>=2.0.0,<3.0.0)
Requires-Dist: aiosmtplib (>=1.1.6,<2.0.0)
Requires-Dist: blinker (>=1.4,<2.0)
Requires-Dist: email-validator (>=1.1.3,<2.0.0)
Requires-Dist: fakeredis (>=1.6.1,<2.0.0)
Requires-Dist: fastapi (>=0.75.0,<0.76.0)
Requires-Dist: httpx (>=0.22.0,<0.23.0)
Requires-Dist: pydantic (>=1.8.2,<2.0.0)
Requires-Dist: python-multipart (>=0.0.5,<0.0.6)
